lib/_init_.py
lib/rumusMatematika.py
main_app_yokaai-0.1.0.dist-info/METADATA
main_app_yokaai-0.1.0.dist-info/WHEEL
main_app_yokaai-0.1.0.dist-info/top_level.txt
main_app_yokaai-0.1.0.dist-info/RECORD
